nofollowback/__init__.py
nofollowback/cli.py
nofollowback/github.py
nofollowback-0.1.1.dist-info/licenses/LICENSE
nofollowback-0.1.1.dist-info/METADATA
nofollowback-0.1.1.dist-info/WHEEL
nofollowback-0.1.1.dist-info/entry_points.txt
nofollowback-0.1.1.dist-info/top_level.txt
nofollowback-0.1.1.dist-info/RECORD
