Metadata-Version: 2.4
Name: nofollowback
Version: 0.1.1
Summary: CLI tool to list GitHub users you follow who don't follow you back.
Author-email: Yongjin Kim <yongjin@example.com>
License: MIT
Requires-Python: >=3.9
License-File: LICENSE
Requires-Dist: requests>=2.31.0
Requires-Dist: click>=8.1.7
Dynamic: license-file
